LICENSE.txt
MANIFEST.in
README.md
setup.cfg
setup.py
cloudspot_license_api.egg-info/PKG-INFO
cloudspot_license_api.egg-info/SOURCES.txt
cloudspot_license_api.egg-info/dependency_links.txt
cloudspot_license_api.egg-info/requires.txt
cloudspot_license_api.egg-info/top_level.txt
cloudspotlicense/__init__.py
cloudspotlicense/api.py
cloudspotlicense/config.py
cloudspotlicense/constants/errors.py
cloudspotlicense/constants/responses.py
cloudspotlicense/endpoints/__init__.py
cloudspotlicense/endpoints/auth.py
cloudspotlicense/endpoints/base.py
cloudspotlicense/models/__init__.py
cloudspotlicense/models/auth.py
cloudspotlicense/models/base.py
cloudspotlicense/models/errors.py