Metadata-Version: 2.1
Name: cloudspot-license-api
Version: 1.3.1
Summary: Wrapper for the Cloudspot License API endpoints
Home-page: https://github.com/Ecosy-EU/cloudspot-license-api
Author: Alexander Schillemans
Author-email: alexander.schillemans@lhs.global
License: GPL-3.0-or-later
Download-URL: https://github.com/Ecosy-EU/cloudspot-license-api/archive/refs/tags/1.3.1.tar.gz
Keywords: cloudspot
Platform: UNKNOWN
Classifier: Development Status :: 3 - Alpha
Classifier: Intended Audience :: Developers
Classifier: Topic :: Software Development :: Build Tools
Classifier: License :: OSI Approved :: GNU General Public License v3 or later (GPLv3+)
Classifier: Programming Language :: Python :: 3.6
License-File: LICENSE.txt
